ms2rescore_rs-0.4.3.dist-info/METADATA
ms2rescore_rs-0.4.3.dist-info/WHEEL
ms2rescore_rs-0.4.3.dist-info/licenses/LICENSE
ms2rescore_rs/__init__.py
ms2rescore_rs/ms2rescore_rs.cp310-win_amd64.pyd
ms2rescore_rs-0.4.3.dist-info/RECORD
