Metadata-Version: 2.4
Name: ms2rescore-rs
Version: 0.4.3
Classifier: Programming Language :: Rust
Classifier: Programming Language :: Python :: Implementation :: CPython
Classifier: Programming Language :: Python :: Implementation :: PyPy
Requires-Dist: pytest ; extra == 'test'
Provides-Extra: test
License-File: LICENSE
Requires-Python: >=3.8
